[{"onez":"2","onej":"10,000,000","twoz":"141","twoj":"116,332","threez":"1,453","threej":"3,000","fourz":"68,072","fourj":"200","fivez":"1,153,672","fivej":"10","sixz":"8,474,162","sixj":"5","dateNum":"2011017"},{"onez":"5","onej":"8,474,497","twoz":"107","twoj":"243,539","threez":"888","threej":"3,000","fourz":"45,160","fourj":"200","fivez":"872,350","fivej":"10","sixz":"6,182,227","sixj":"5","dateNum":"2011016"},{"onez":"9","onej":"5,803,866","twoz":"110","twoj":"98,656","threez":"1,888","threej":"3,000","fourz":"78,844","fourj":"200","fivez":"1,231,340","fivej":"10","sixz":"10,984,160","sixj":"5","dateNum":"2011015"},{"onez":"7","onej":"7,010,883","twoz":"156","twoj":"135,347","threez":"1,063","threej":"3,000","fourz":"57,004","fourj":"200","fivez":"1,066,585","fivej":"10","sixz":"6,793,351","sixj":"5","dateNum":"2011014"},{"onez":"8","onej":"6,495,969","twoz":"41","twoj":"437,844","threez":"1,068","threej":"3,000","fourz":"52,654","fourj":"200","fivez":"971,075","fivej":"10","sixz":"11,647,863","sixj":"5","dateNum":"2011013"},{"onez":"4","onej":"9,366,150","twoz":"124","twoj":"211,265","threez":"748","threej":"3,000","fourz":"43,871","fourj":"200","fivez":"989,282","fivej":"10","sixz":"3,871,774","sixj":"5","dateNum":"2011012"},{"onez":"10","onej":"5,829,648","twoz":"73","twoj":"170,475","threez":"1,470","threej":"3,000","fourz":"61,201","fourj":"200","fivez":"1,041,528","fivej":"10","sixz":"11,321,407","sixj":"5","dateNum":"2011011"},{"onez":"9","onej":"6,680,151","twoz":"118","twoj":"192,220","threez":"1,279","threej":"3,000","fourz":"60,258","fourj":"200","fivez":"1,133,364","fivej":"10","sixz":"7,508,480","sixj":"5","dateNum":"2011010"},{"onez":"3","onej":"9,130,252","twoz":"90","twoj":"206,512","threez":"1,157","threej":"3,000","fourz":"49,709","fourj":"200","fivez":"964,217","fivej":"10","sixz":"8,931,607","sixj":"5","dateNum":"2011009"},{"onez":"3","onej":"10,000,000","twoz":"50","twoj":"508,546","threez":"526","threej":"3,000","fourz":"30,996","fourj":"200","fivez":"676,542","fivej":"10","sixz":"5,528,732","sixj":"5","dateNum":"2011008"},{"onez":"6","onej":"8,274,578","twoz":"96","twoj":"306,991","threez":"810","threej":"3,000","fourz":"41,380","fourj":"200","fivez":"860,402","fivej":"10","sixz":"5,199,506","sixj":"5","dateNum":"2011007"},{"onez":"2","onej":"10,000,000","twoz":"95","twoj":"280,087","threez":"646","threej":"3,000","fourz":"40,071","fourj":"200","fivez":"868,586","fivej":"10","sixz":"4,530,327","sixj":"5","dateNum":"2011006"},{"onez":"1","onej":"10,000,000","twoz":"109","twoj":"225,893","threez":"792","threej":"3,000","fourz":"41,587","fourj":"200","fivez":"833,037","fivej":"10","sixz":"5,102,477","sixj":"5","dateNum":"2011005"},{"onez":"2","onej":"7,500,000","twoz":"119","twoj":"213,471","threez":"1,052","threej":"3,000","fourz":"59,457","fourj":"200","fivez":"1,206,923","fivej":"10","sixz":"5,446,687","sixj":"5","dateNum":"2011004"},{"onez":"14","onej":"5,060,062","twoz":"50","twoj":"6,000","threez":"3,117","threej":"3,000","fourz":"116,642","fourj":"200","fivez":"1,605,741","fivej":"10","sixz":"18,033,822","sixj":"5","dateNum":"2011003"},{"onez":"7","onej":"5,714,285","twoz":"102","twoj":"188,201","threez":"1,350","threej":"3,000","fourz":"62,867","fourj":"200","fivez":"1,111,740","fivej":"10","sixz":"8,166,452","sixj":"5","dateNum":"2011002"},{"onez":"9","onej":"5,555,555","twoz":"76","twoj":"215,612","threez":"1,415","threej":"3,000","fourz":"64,184","fourj":"200","fivez":"1,125,120","fivej":"10","sixz":"11,899,684","sixj":"5","dateNum":"2011001"},{"onez":"15","onej":"5,333,333","twoz":"124","twoj":"166,902","threez":"1,534","threej":"3,000","fourz":"64,074","fourj":"200","fivez":"1,086,763","fivej":"10","sixz":"8,743,666","sixj":"5","dateNum":"2010153"},{"onez":"11","onej":"5,454,545","twoz":"244","twoj":"104,789","threez":"1,168","threej":"3,000","fourz":"58,077","fourj":"200","fivez":"1,059,248","fivej":"10","sixz":"5,619,134","sixj":"5","dateNum":"2010152"},{"onez":"6","onej":"5,833,333","twoz":"99","twoj":"329,655","threez":"519","threej":"3,000","fourz":"34,674","fourj":"200","fivez":"815,044","fivej":"10","sixz":"5,834,033","sixj":"5","dateNum":"2010151"}]