[{"onez":"0","onej":"5,000,000","twoz":"53","twoj":"435,162","threez":"392","threej":"3,000","fourz":"22,280","fourj":"200","fivez":"471,472","fivej":"10","sixz":"2,106,560","sixj":"5","dateNum":"2006045"},{"onez":"0","onej":"5,000,000","twoz":"24","twoj":"783,393","threez":"431","threej":"3,000","fourz":"20,493","fourj":"200","fivez":"358,269","fivej":"10","sixz":"3,321,865","sixj":"5","dateNum":"2006044"},{"onez":"2","onej":"5,000,000","twoz":"36","twoj":"863,576","threez":"244","threej":"3,000","fourz":"16,643","fourj":"200","fivez":"364,465","fivej":"10","sixz":"1,888,909","sixj":"5","dateNum":"2006043"},{"onez":"1","onej":"5,000,000","twoz":"7","twoj":"2,094,597","threez":"291","threej":"3,000","fourz":"15,836","fourj":"200","fivez":"291,600","fivej":"10","sixz":"4,780,445","sixj":"5","dateNum":"2006042"},{"onez":"2","onej":"5,000,000","twoz":"49","twoj":"447,691","threez":"362","threej":"3,000","fourz":"19,236","fourj":"200","fivez":"364,581","fivej":"10","sixz":"2,377,593","sixj":"5","dateNum":"2006041"},{"onez":"0","onej":"5,000,000","twoz":"20","twoj":"1,638,243","threez":"159","threej":"3,000","fourz":"10,911","fourj":"200","fivez":"279,441","fivej":"10","sixz":"1,636,440","sixj":"5","dateNum":"2006040"},{"onez":"1","onej":"5,000,000","twoz":"18","twoj":"1,067,405","threez":"298","threej":"3,000","fourz":"14,798","fourj":"200","fivez":"303,074","fivej":"10","sixz":"3,546,942","sixj":"5","dateNum":"2006039"},{"onez":"2","onej":"5,000,000","twoz":"32","twoj":"510,825","threez":"391","threej":"3,000","fourz":"21,824","fourj":"200","fivez":"395,617","fivej":"10","sixz":"3,426,454","sixj":"5","dateNum":"2006038"},{"onez":"1","onej":"5,000,000","twoz":"59","twoj":"489,240","threez":"337","threej":"3,000","fourz":"18,227","fourj":"200","fivez":"368,473","fivej":"10","sixz":"2,279,534","sixj":"5","dateNum":"2006037"},{"onez":"1","onej":"5,000,000","twoz":"38","twoj":"535,680","threez":"437","threej":"3,000","fourz":"22,982","fourj":"200","fivez":"428,631","fivej":"10","sixz":"2,909,805","sixj":"5","dateNum":"2006036"},{"onez":"2","onej":"5,000,000","twoz":"117","twoj":"217,115","threez":"238","threej":"3,000","fourz":"23,853","fourj":"200","fivez":"482,206","fivej":"10","sixz":"1,218,057","sixj":"5","dateNum":"2006035"},{"onez":"4","onej":"5,000,000","twoz":"38","twoj":"599,172","threez":"406","threej":"3,000","fourz":"21,512","fourj":"200","fivez":"406,553","fivej":"10","sixz":"4,206,949","sixj":"5","dateNum":"2006034"},{"onez":"0","onej":"0","twoz":"5","twoj":"4,333,749","threez":"198","threej":"3,000","fourz":"12,848","fourj":"200","fivez":"283,094","fivej":"10","sixz":"3,504,017","sixj":"5","dateNum":"2006033"},{"onez":"4","onej":"5,000,000","twoz":"24","twoj":"501,510","threez":"689","threej":"3,000","fourz":"29,263","fourj":"200","fivez":"479,909","fivej":"10","sixz":"4,886,137","sixj":"5","dateNum":"2006032"},{"onez":"0","onej":"5,000,000","twoz":"16","twoj":"2,063,012","threez":"178","threej":"3,000","fourz":"12,785","fourj":"200","fivez":"341,801","fivej":"10","sixz":"1,430,890","sixj":"5","dateNum":"2006031"},{"onez":"0","onej":"5,000,000","twoz":"21","twoj":"430,496","threez":"399","threej":"3,000","fourz":"19,574","fourj":"200","fivez":"399,840","fivej":"10","sixz":"2,343,750","sixj":"5","dateNum":"2006030"},{"onez":"3","onej":"5,000,000","twoz":"28","twoj":"241,349","threez":"512","threej":"3,000","fourz":"25,657","fourj":"200","fivez":"473,666","fivej":"10","sixz":"3,119,470","sixj":"5","dateNum":"2006029"},{"onez":"3","onej":"5,000,000","twoz":"40","twoj":"119,296","threez":"792","threej":"3,000","fourz":"33,425","fourj":"200","fivez":"552,093","fivej":"10","sixz":"5,230,668","sixj":"5","dateNum":"2006028"},{"onez":"2","onej":"5,000,000","twoz":"27","twoj":"491,533","threez":"633","threej":"3,000","fourz":"27,047","fourj":"200","fivez":"455,807","fivej":"10","sixz":"4,132,131","sixj":"5","dateNum":"2006027"},{"onez":"2","onej":"5,000,000","twoz":"19","twoj":"817,165","threez":"450","threej":"3,000","fourz":"21,373","fourj":"200","fivez":"388,480","fivej":"10","sixz":"3,628,434","sixj":"5","dateNum":"2006026"}]